harpoontools/tools.py
harpoontools-0.1.7.dist-info/LICENSE
harpoontools-0.1.7.dist-info/METADATA
harpoontools-0.1.7.dist-info/WHEEL
harpoontools-0.1.7.dist-info/entry_points.txt
harpoontools-0.1.7.dist-info/top_level.txt
harpoontools-0.1.7.dist-info/RECORD
