Metadata-Version: 2.1
Name: harpoontools
Version: 0.1.7
Summary: CLI tools going with Harpoon
Home-page: https://github.com/Te-k/harpoontools
Author: Tek
Author-email: tek@randhome.io
License: GPLv3
Keywords: osint
Classifier: Programming Language :: Python :: 3
Classifier: License :: OSI Approved :: MIT License
Classifier: Operating System :: OS Independent
Requires-Python: >=3.5
License-File: LICENSE
Requires-Dist: requests
Requires-Dist: harpoon (==0.1.7)
